README.md
setup.cfg
setup.py
vowel/Gridlayout.py
vowel/SemaphoreDemo.py
vowel/__init__.py
vowel/action.py
vowel/addmatrix.py
vowel/agexept.py
vowel/animals.py
vowel/awtstudinfo.py
vowel/bank.py
vowel/bgcolor.py
vowel/borderlayout.py
vowel/byteread.py
vowel/c_basics.py
vowel/c_dijkstra.py
vowel/c_euler.py
vowel/c_ford.py
vowel/c_graph_color.py
vowel/c_ham.py
vowel/c_kruskal.py
vowel/c_prims.py
vowel/c_terms.py
vowel/calcawt.py
vowel/copyfile.py
vowel/d_calbill.py
vowel/d_calbonus.py
vowel/d_calsal.py
vowel/d_caltadahra.py
vowel/d_casegrade.py
vowel/d_circle.py
vowel/d_circtable.py
vowel/d_del_trigger.py
vowel/d_discount.py
vowel/d_displayexp.py
vowel/d_emp_sal_trigger.py
vowel/d_empsalinc.py
vowel/d_exitwhen.py
vowel/d_exitwhensimpleloop.py
vowel/d_funcfactrecursion.py
vowel/d_funcmaxnum.py
vowel/d_functotalemp.py
vowel/d_goto.py
vowel/d_grt3num.py
vowel/d_ifelsif.py
vowel/d_ifendif.py
vowel/d_inctax.py
vowel/d_lobtimestamp.py
vowel/d_mult.py
vowel/d_prime.py
vowel/d_procfact.py
vowel/d_prochello.py
vowel/d_procinsdata.py
vowel/d_proclectureranswer.py
vowel/d_procswap.py
vowel/d_procswap2.py
vowel/d_savepoint.py
vowel/d_seq_emp.py
vowel/d_seq_patient.py
vowel/d_seq_stud.py
vowel/d_simpleloopctrl.py
vowel/d_sqr.py
vowel/d_srchdcase.py
vowel/d_strfunc.py
vowel/d_stringvar.py
vowel/d_subtype.py
vowel/d_sum100.py
vowel/d_sum100num.py
vowel/d_tablebook.py
vowel/d_tablemalaria.py
vowel/d_tableplace.py
vowel/d_tablesupplier.py
vowel/d_ticket.py
vowel/d_trig_extra.py
vowel/d_trigger_view.py
vowel/d_trim.py
vowel/d_usriprt.py
vowel/d_varscope.py
vowel/d_while.py
vowel/d_withcasestatement.py
vowel/d_withoutcasestatement.py
vowel/draw.py
vowel/empfile.py
vowel/extendhrd.py
vowel/fcfs.py
vowel/fifopgrepl.py
vowel/filewriter.py
vowel/fptrinc.py
vowel/i_add2numhtml.py
vowel/i_aplusb.py
vowel/i_blinkled.py
vowel/i_bread.py
vowel/i_btn.py
vowel/i_camera.py
vowel/i_chart.py
vowel/i_date.py
vowel/i_fibo.py
vowel/i_gaugeslider.py
vowel/i_led.py
vowel/i_matrix.py
vowel/i_motor.py
vowel_versificon.egg-info/PKG-INFO
vowel_versificon.egg-info/SOURCES.txt
vowel_versificon.egg-info/dependency_links.txt
vowel_versificon.egg-info/top_level.txt