Metadata-Version: 2.1
Name: vowel-versificon
Version: 0.0.22
Summary: A small example package
Home-page: https://github.com/pypa/sampleproject
Author: Python
Author-email: python@example.com
License: UNKNOWN
Platform: UNKNOWN
Classifier: Programming Language :: Python :: 3
Classifier: License :: OSI Approved :: MIT License
Classifier: Operating System :: OS Independent
Requires-Python: >=3.4
